main.py
nearby_search_mcp-0.1.0.dist-info/licenses/LICENSE
nearby_search_mcp-0.1.0.dist-info/METADATA
nearby_search_mcp-0.1.0.dist-info/WHEEL
nearby_search_mcp-0.1.0.dist-info/top_level.txt
nearby_search_mcp-0.1.0.dist-info/RECORD
