Metadata-Version: 2.4
Name: nearby-search-mcp
Version: 0.1.0
Summary: An MCP server for nearby place searches with IP-based location detection.
Requires-Python: >=3.13
License-File: LICENSE
Requires-Dist: dotenv>=0.9.9
Requires-Dist: httpx>=0.28.1
Requires-Dist: mcp[cli]>=1.4.1
Dynamic: license-file
